{"cameraMode":{"drawMode":0,"name":"Shaded","section":"Shading Mode"},"sceneLighting":true,"audioPlay":false,"sceneViewState":{"m_AlwaysRefresh":false,"showFog":true,"showSkybox":true,"showFlares":true,"showImageEffects":true,"showParticleSystems":true,"showVisualEffectGraphs":true,"m_FxEnabled":true},"in2DMode":false,"pivot":{"x":-1.7192506790161133,"y":-4.863525390625,"z":2.105417013168335},"rotation":{"x":-0.37114131450653078,"y":0.6265833377838135,"z":-0.44969117641448977,"w":-0.5171306729316711},"size":6.504177093505859,"orthographic":false}